odoo/addons/web_no_bubble/README.rst
odoo/addons/web_no_bubble/__init__.py
odoo/addons/web_no_bubble/__manifest__.py
odoo/addons/web_no_bubble/i18n/es.po
odoo/addons/web_no_bubble/i18n/fr_FR.po
odoo/addons/web_no_bubble/i18n/hr.po
odoo/addons/web_no_bubble/i18n/it.po
odoo/addons/web_no_bubble/i18n/web_no_bubble.pot
odoo/addons/web_no_bubble/i18n/zh_CN.po
odoo/addons/web_no_bubble/readme/CONTRIBUTORS.md
odoo/addons/web_no_bubble/readme/DESCRIPTION.md
odoo/addons/web_no_bubble/static/description/icon.png
odoo/addons/web_no_bubble/static/description/index.html
odoo/addons/web_no_bubble/static/src/css/web_no_bubble.scss
odoo_addon_web_no_bubble-18.0.1.0.0.2.dist-info/METADATA
odoo_addon_web_no_bubble-18.0.1.0.0.2.dist-info/WHEEL
odoo_addon_web_no_bubble-18.0.1.0.0.2.dist-info/top_level.txt
odoo_addon_web_no_bubble-18.0.1.0.0.2.dist-info/RECORD
